{
  "run_id": "run_103",
  "task_id": "HE_004_5",
  "task": "Check if a binary tree is balanced",
  "pass_at_1": true,
  "passed": true,
  "k_used": 1,
  "elapsed_sec": 111.9,
  "events": [
    {
      "ts": 1713063736,
      "event": "session_start",
      "run_id": "run_103",
      "task_id": "HE_004_5"
    },
    {
      "ts": 1713063736.5,
      "event": "agent_start",
      "agent": "planner",
      "task": "Check if a binary tree is balanced"
    },
    {
      "ts": 1713063739.0760157,
      "event": "agent_done",
      "agent": "planner",
      "mode": "coding"
    },
    {
      "ts": 1713063739.2760158,
      "event": "agent_start",
      "agent": "coder"
    },
    {
      "ts": 1713063754.2757819,
      "event": "agent_done",
      "agent": "coder",
      "tokens": 358
    },
    {
      "ts": 1713063754.5757818,
      "event": "agent_start",
      "agent": "tester",
      "iteration": 1
    },
    {
      "ts": 1713063756.884442,
      "event": "test_result",
      "iteration": 1,
      "total": 3,
      "passed": 3,
      "failed": 0,
      "verdict": "PASS"
    },
    {
      "ts": 1713063757.384442,
      "event": "agent_start",
      "agent": "critic"
    },
    {
      "ts": 1713063760.9075112,
      "event": "review",
      "verdict": "PASS",
      "score": 8.6
    },
    {
      "ts": 1713063761.1075113,
      "event": "session_end",
      "run_id": "run_103",
      "passed": true,
      "elapsed_sec": 111.9,
      "k_iterations": 1,
      "agents_used": [
        "planner",
        "coder",
        "tester",
        "debugger",
        "critic"
      ]
    }
  ]
}